langchain_agent/__init__.py
langchain_agent/agent.py
langchain_agent/config.py
langchain_agent/main.py
langchain_agent/tools.py
langchain_agent/utils.py
langchain_agent-0.1.1.dist-info/METADATA
langchain_agent-0.1.1.dist-info/WHEEL
langchain_agent-0.1.1.dist-info/entry_points.txt
langchain_agent-0.1.1.dist-info/licenses/LICENSE
langchain_agent-0.1.1.dist-info/RECORD
