Metadata-Version: 2.4
Name: langchain_agent
Version: 0.1.1
Summary: A LangChain-based chat agent with tool integration
Project-URL: Homepage, https://github.com/yourusername/langchain_agent
Project-URL: Documentation, https://github.com/yourusername/langchain_agent#readme
Project-URL: Repository, https://github.com/yourusername/langchain_agent.git
Project-URL: Issues, https://github.com/yourusername/langchain_agent/issues
Author-email: Your Name <your.email@example.com>
License: MIT
License-File: LICENSE
Keywords: agent,ai,chatbot,langchain,llm
Classifier: Development Status :: 3 - Alpha
Classifier: Intended Audience :: Developers
Classifier: License :: OSI Approved :: MIT License
Classifier: Programming Language :: Python :: 3
Classifier: Programming Language :: Python :: 3.10
Classifier: Programming Language :: Python :: 3.11
Classifier: Programming Language :: Python :: 3.12
Classifier: Topic :: Scientific/Engineering :: Artificial Intelligence
Classifier: Topic :: Software Development :: Libraries :: Python Modules
Requires-Python: >=3.10
Requires-Dist: langchain-ollama>=1.0.0
Requires-Dist: langchain>=1.0.3
Requires-Dist: python-dotenv>=1.0.0
Provides-Extra: dev
Requires-Dist: black>=23.0.0; extra == 'dev'
Requires-Dist: flake8>=6.0.0; extra == 'dev'
Requires-Dist: mypy>=1.0.0; extra == 'dev'
Requires-Dist: pytest-cov>=4.0.0; extra == 'dev'
Requires-Dist: pytest>=7.0.0; extra == 'dev'
